django_mistune/__about__.py
django_mistune/__init__.py
django_mistune/conf.py
django_mistune/plugins.py
django_mistune/utils.py
django_mistune/templatetags/__init__.py
django_mistune/templatetags/mistune.py
django_mistune-0.3.1.dist-info/METADATA
django_mistune-0.3.1.dist-info/WHEEL
django_mistune-0.3.1.dist-info/licenses/LICENSE.txt
django_mistune-0.3.1.dist-info/RECORD
